{
	"name": "starry code",
	  "$schema": "vscode://schemas/color-theme",
	  "type": "dark",
	  "colors": {
		"activityBar.background": "#2b2f47",
		"activityBar.foreground": "#CBD5EA",
		"activityBarBadge.background": "#4f71c5",
		"activityBarBadge.foreground": "#050505",
		"badge.background": "#6a6af14b",
		"badge.foreground": "#6375a1",
		"breadcrumb.activeSelectionForeground": "#A2B2CE",
		"breadcrumb.background": "#272731",
		"breadcrumb.focusForeground": "#A6C1D1",
		"breadcrumb.foreground": "#669EED",
		"breadcrumbPicker.background": "#272731",
		"button.background": "#3C488E",
		"debugToolBar.background": "#272731",
		"diffEditor.insertedTextBackground": "#BCA42715",
		"diffEditor.removedTextBackground": "#A1B99D20",
		"dropdown.background": "#272731",
		"dropdown.border": "#fbe5ba00",
		"editor.background": "#272731",
		"editor.findMatchBackground": "#272731",
		"editor.findMatchBorder": "#376aeb5b",
		"editor.findMatchHighlightBackground": "#3F64BF93",
		"editor.findMatchHighlightBorder": "#FBE5BA30",
		"editor.foreground": "#badcf0",
		"editor.lineHighlightBackground": "#27273150",
		"editor.selectionBackground": "#DBD0F630",
		"editor.selectionHighlightBackground": "#3F64BF6b",
		"editor.selectionHighlightBorder": "#DBD0F6f0",
		"editorBracketMatch.background": "#272731",
		"editorBracketMatch.border": "#DACD7D7f",
		"editorCursor.foreground": "#DACD7D",
		"editorError.foreground": "#a1b99d00",
		"editorGroup.border": "#27273130",
		"editorGroupHeader.tabsBackground": "#272731",
		"editorGutter.addedBackground": "#BCA42760",
		"editorGutter.deletedBackground": "#A1B99D60",
		"editorGutter.modifiedBackground": "#DBD0F660",
		"editorHoverWidget.background": "#272731",
		"editorHoverWidget.border": "#FBE5BA10",
		"editorIndentGuide.activeBackground": "#646A8E",
		"editorIndentGuide.background": "#646A8E70",
		"editorInfo.foreground": "#DBD0F670",
		"editorLineNumber.activeForeground": "#DBD0F6",
		"editorLineNumber.foreground": "#3f63bf46",
		"editorLink.activeForeground": "#a6c1d196",
		"editorMarkerNavigation.background": "#A6C1D105",
		"editorOverviewRuler.border": "#272731",
		"editorOverviewRuler.errorForeground": "#A1B99D40",
		"editorOverviewRuler.findMatchForeground": "#3F64BF",
		"editorOverviewRuler.infoForeground": "#DBD0F640",
		"editorOverviewRuler.warningForeground": "#DACD7D70",
		"editorRuler.foreground": "#646A8E",
		"editorSuggestWidget.background": "#272731",
		"editorSuggestWidget.border": "#FBE5BA10",
		"editorSuggestWidget.foreground": "#A6C1D1",
		"editorSuggestWidget.highlightForeground": "#DACD7D",
		"editorSuggestWidget.selectedBackground": "#3F64BF20",
		"editorWarning.foreground": "#BCA427",
		"editorWhitespace.foreground": "#A6C1D140",
		"editorWidget.background": "#272731",
		"editorWidget.border": "#DACD7D",
		"editorWidget.resizeBorder": "#3F64BF",
		"extensionButton.prominentBackground": "#BCA42790",
		"extensionButton.prominentHoverBackground": "#A1B99D",
		"focusBorder": "#FBE5BA00",
		"gitDecoration.conflictingResourceForeground": "#DACD7D",
		"gitDecoration.deletedResourceForeground": "#A1B99D",
		"gitDecoration.ignoredResourceForeground": "#3F64BF",
		"gitDecoration.modifiedResourceForeground": "#669EED",
		"gitDecoration.untrackedResourceForeground": "#DBD0F6",
		"input.background": "#454C66",
		"input.border": "#FBE5BA10",
		"input.foreground": "#A6C1D1",
		"input.placeholderForeground": "#A6C1D160",
		"inputOption.activeBackground": "#A6C1D130",
		"inputOption.activeBorder": "#A6C1D130",
		"inputValidation.errorBorder": "#A1B99D50",
		"inputValidation.infoBorder": "#DBD0F650",
		"inputValidation.warningBorder": "#DACD7D50",
		"list.activeSelectionBackground": "#272731",
		"list.activeSelectionForeground": "#3F64BF",
		"list.focusBackground": "#454C66",
		"list.focusForeground": "#DBD0F6",
		"list.highlightForeground": "#3F64BF",
		"list.hoverBackground": "#646A8E",
		"list.hoverForeground": "#FBE5BA",
		"list.inactiveSelectionBackground": "#27273130",
		"list.inactiveSelectionForeground": "#3F64BF",
		"list.warningForeground": "#DACD7D",
		"listFilterWidget.background": "#27273130",
		"listFilterWidget.noMatchesOutline": "#27273130",
		"listFilterWidget.outline": "#27273130",
		"menu.background": "#272731f8",
		"menu.border": "#3F64BF50",
		"menu.foreground": "#A6C1D1",
		"menu.selectionBackground": "#454C66",
		"menu.selectionBorder": "#27273130",
		"menu.selectionForeground": "#A6C1D1",
		"menu.separatorBackground": "#A6C1D1",
		"menubar.selectionBackground": "#454C66",
		"menubar.selectionBorder": "#3F64BF50",
		"menubar.selectionForeground": "#A6C1D1",
		"minimap.background": "#272731",
		"minimapGutter.addedBackground": "#A1B99D",
		"minimapGutter.deletedBackground": "#DACD7D",
		"minimapGutter.modifiedBackground": "#BCA427",
		"minimapSlider.activeBackground": "#BCA427b0",
		"minimapSlider.background": "#BCA42780",
		"minimapSlider.hoverBackground": "#BCA427a0",
		"notificationLink.foreground": "#3F64BF",
		"notifications.background": "#272731",
		"notifications.foreground": "#A6C1D1",
		"panel.background": "#272731",
		"panel.border": "#27273160",
		"panelTitle.activeBorder": "#3F64BF",
		"panelTitle.activeForeground": "#FBE5BA",
		"panelTitle.inactiveForeground": "#A6C1D1",
		"peekView.border": "#27273130",
		"peekViewEditor.background": "#A6C1D105",
		"peekViewEditor.matchHighlightBackground": "#3F64BF50",
		"peekViewEditorGutter.background": "#A6C1D105",
		"peekViewResult.background": "#A6C1D105",
		"peekViewResult.matchHighlightBackground": "#3F64BF50",
		"peekViewResult.selectionBackground": "#3F64BF70",
		"peekViewTitle.background": "#A6C1D105",
		"peekViewTitleDescription.foreground": "#A6C1D160",
		"pickerGroup.foreground": "#3F64BF",
		"progressBar.background": "#3F64BF",
		"scrollbar.shadow": "#27273100",
		"scrollbarSlider.activeBackground": "#3f63bf4b",
		"scrollbarSlider.background": "#3f63bf4b",
		"selection.background": "#3F64BF",
		"settings.checkboxBackground": "#272731",
		"settings.checkboxForeground": "#A6C1D1",
		"settings.dropdownBackground": "#272731",
		"settings.dropdownForeground": "#A6C1D1",
		"settings.headerForeground": "#3F64BF",
		"settings.modifiedItemIndicator": "#3F64BF",
		"settings.numberInputBackground": "#272731",
		"settings.numberInputForeground": "#A6C1D1",
		"settings.textInputBackground": "#272731",
		"settings.textInputForeground": "#A6C1D1",
		"sideBar.background": "#272731",
		"sideBar.foreground": "#dbd0f6ad",
		"sideBarSectionHeader.background": "#272731",
		"sideBarSectionHeader.foreground": "#DBD0F6",
		"sideBarTitle.foreground": "#A6C1D1",
		"statusBar.background": "#2c346671",
		"statusBar.debuggingBackground": "#DACD7D",
		"statusBar.debuggingForeground": "#FBE5BA",
		"statusBar.foreground": "#e2dccb",
		"statusBar.noFolderBackground": "#272731",
		"statusBarItem.hoverBackground": "#3F64BF20",
		"statusBarItem.remoteBackground": "#3F64BF",
		"statusBarItem.remoteForeground": "#272731",
		"tab.activeBackground": "#22335e60",
		"tab.activeBorder": "#3F64BF",
		"tab.activeForeground": "#FBE5BA",
		"tab.activeModifiedBorder": "#3F64BF",
		"tab.inactiveBackground": "#3f63bf09",
		"tab.inactiveForeground": "#a6c1d18e",
		"tab.unfocusedActiveBorder": "#3F64BF",
		"tab.unfocusedActiveBackground": "#3F64BF40",
		"tab.unfocusedActiveForeground": "#A6C1D1",
		"tab.unfocusedInactiveBackground": "#3F64BF10",
		"tab.unfocusedInactiveForeground": "#A6C1D17f",
		"terminal.ansiBlack": "#272731",
		"terminal.ansiBlue": "#DBD0F6",
		"terminal.ansiBrightBlack": "#3F64BF",
		"terminal.ansiBrightBlue": "#DBD0F6",
		"terminal.ansiBrightCyan": "#DFDFEE",
		"terminal.ansiBrightGreen": "#BCA427",
		"terminal.ansiBrightMagenta": "#DACD7D",
		"terminal.ansiBrightRed": "#A1B99D",
		"terminal.ansiBrightWhite": "#FBE5BA",
		"terminal.ansiBrightYellow": "#DACD7D",
		"terminal.ansiCyan": "#DFDFEE",
		"terminal.ansiGreen": "#BCA427",
		"terminal.ansiMagenta": "#DACD7D",
		"terminal.ansiRed": "#A1B99D",
		"terminal.ansiWhite": "#FBE5BA",
		"terminal.ansiYellow": "#DACD7D",
		"terminalCursor.background": "#272731",
		"terminalCursor.foreground": "#DACD7D",
		"textLink.activeForeground": "#A6C1D1",
		"textLink.foreground": "#3F64BF",
		"titleBar.activeBackground": "#272731",
		"titleBar.activeForeground": "#A6C1D1",
		"titleBar.border": "#27273160",
		"titleBar.inactiveBackground": "#272731",
		"titleBar.inactiveForeground": "#3F64BF",
		"tree.indentGuidesStroke": "#646A8E",
		"widget.shadow": "#27273130",
	  },
	  "tokenColors": [
		{
		  "scope": [
			"variable",
			"string constant.other.placeholder",
			"invalid.deprecated",
			"keyword",
			"storage.type",
			"storage.modifier"
		  ],
		  "settings": {
			"foreground": "#DACD7D"
		  }
		},
		{
		  "scope": [
			"variable",
			"string constant.other.placeholder",
			"entity.name.function",
			"punctuation.definition.interpolation.end.bracket.curly.scss",
			"punctuation.definition.interpolation.begin.bracket.curly.scss"
		  ],
		  "settings": {
			"fontStyle": "italic"
		  }
		},
		{
		  "scope": [
			"punctuation.definition.interpolation.end.bracket.curly.scss",
			"punctuation.definition.interpolation.begin.bracket.curly.scss"
		  ],
		  "settings": {
			"foreground": "#BCA427"
		  }
		},
		{
		  "scope": [
			"constant.other.php"
		  ],
		  "settings": {
			"foreground": "#DACD7D"
		  }
		},
		{
		  "scope": [
			"constant.other.color"
		  ],
		  "settings": {
			"foreground": "#FBE5BA"
		  }
		},
		{
		  "scope": [
			"invalid",
			"invalid.illegal"
		  ],
		  "settings": {
			"foreground": "#A1B99D"
		  }
		},
		{
		  "scope": [
			"Keyword",
			"Storage"
		  ],
		  "settings": {
			"fontStyle": "italic"
		  }
		},
		{
		  "scope": [
			"keyword.control",
			"constant.other.color",
			"punctuation.definition.tag",
			"punctuation",
			"punctuation.separator.inheritance.php",
			"punctuation.definition.tag.html",
			"punctuation.section.embedded",
			"keyword.other.template",
			"keyword.other.substitution",
			"entity.name.tag.reference.scss"
		  ],
		  "settings": {
			"foreground": "#81A1C1"
		  }
		},
		{
		  "scope": [
			"punctuation.definition.tag.begin.html",
			"punctuation.definition.tag.end.html",
			"entity.name.type.module.js"
		  ],
		  "settings": {
			"foreground": "#849C81"
		  }
		},
		{
		  "scope": [
			"keyword.control.at-rule",
			"punctuation.terminator.rule.css",
			"keyword.control.operator",
			"punctuation.definition.entity.css",
			"keyword.operator.assignment.js",
			"punctuation.separator.comma.js",
			"punctuation.definition.string.begin.js",
			"punctuation.definition.string.end.js",
			"punctuation.definition.binding-pattern.object.js"
		  ],
		  "settings": {
			"foreground": "#A3BE8C"
		  }
		},
		{
		  "scope": [
			"punctuation.definition",
			"string.quoted.single.scss"
		  ],
		  "settings": {
			"foreground": "#A7A8AF"
		  }
		},
		{
		  "scope": [
			"keyword.control"
		  ],
		  "settings": {
			"fontStyle": "italic"
		  }
		},
		{
		  "scope": [
			"comment.line.scss",
			"comment.line.double-slash.js",
			"punctuation.definition.comment.scss",
			"punctuation.definition.comment.js",
			"punctuation.definition.comment.html",
			"comment.block.html"
		  ],
		  "settings": {
			"foreground": "#6D6F7C"
		  }
		},
		{
		  "scope": [
			"text.html.derivative"
		  ],
		  "settings": {
			"foreground": "#FDF1BF"
		  }
		},
		{
		  "scope": [
			"entity.name.tag",
			"meta.tag.sgml",
			"markup.deleted.git_gutter"
		  ],
		  "settings": {
			"foreground": "#A0B99B"
		  }
		},
		{
		  "scope": [
			"entity.name.tag.html"
		  ],
		  "settings": {
			"fontStyle": "italic"
		  }
		},
		{
		  "scope": [
			"variable.parameter.js",
			"variable.parameter.keyframe-list.css"
		  ],
		  "settings": {
			"foreground": "#DACD7D"
		  }
		},
		{
		  "scope": [
			"variable.other.object.js",
			"storage.type.js",
			"string.other.link.title.markdown",
			"variable.other.readwrite.js",
			"variable.other.property.js"
		  ],
		  "settings": {
			"foreground": "#446CCF",
			"fontStyle": "bold"
		  }
		},
		{
		  "scope": [
			"string",
			"string.quoted.double.html",
			"variable.other.constant.js",
			"variable.other.object.property.js",
			"string.quoted.double.json",
			"markup.fenced_code.block.markdown",
			"markup.inline.raw.string.markdown",
			"variable.function",
			"keyword.other.special-method",
			"entity.name.function",
			"markup.bold",
			"markup.bold.markdown",
			"markup.italic.markdown",
			"meta.class-method.js entity.name.function.js",
			"variable.function.constructor",
			"entity.name.tag.other.html",
			"entity.name.tag.block.any.html",
			"source.sass keyword.control"
		  ],
		  "settings": {
			"foreground": "#7B9AD4"
		  }
		},
		{
		  "scope": [
			"punctuation.definition.string.begin.html",
			"punctuation.definition.string.end.html"
		  ],
		  "settings": {
			"foreground": "#A3BE8C"
		  }
		},
		{
		  "scope": [
			"support.other.variable",
			"string.other.link",
			"markup.table"
		  ],
		  "settings": {
			"foreground": "#A6C1D1"
		  }
		},
		{
		  "scope": [
			"constant.numeric",
			"constant.language",
			"constant.character",
			"constant.escape",
			"keyword.other.unit",
			"keyword.other",
			"punctuation.separator.key-value.html"
		  ],
		  "settings": {
			"foreground": "#A0B99B"
		  }
		},
		{
		  "scope": [
			"variable.parameter.function.language.special",
			"variable.parameter"
		  ],
		  "settings": {
			"foreground": "#A1B99D"
		  }
		},
		{
		  "scope": [
			"constant.other.symbol",
			"constant.other.key",
			"entity.other.inherited-class",
			"keyword.other.unit",
			"markup.heading",
			"markup.inserted.git_gutter",
			"meta.group.braces.curly",
			"constant.other.object.key.js",
			"string.unquoted.label.js"
		  ],
		  "settings": {
			"foreground": "#A0B99B",
			"fontStyle": ""
		  }
		},
		{
		  "scope": [
			"entity.name",
			"support.type",
			"support.class",
			"support.orther.namespace.use.php",
			"meta.use.php",
			"support.other.namespace.php",
			"markup.changed.git_gutter",
			"support.type.sys-types",
			"entity.other.attribute-name.html"
		  ],
		  "settings": {
			"foreground": "#DACD7D"
		  }
		},
		{
		  "scope": [
			"support.type"
		  ],
		  "settings": {
			"foreground": "#B2CCD6"
		  }
		},
		{
		  "scope": [
			"source.css support.type.property-name",
			"source.sass support.type.property-name",
			"source.scss support.type.property-name",
			"source.less support.type.property-name",
			"source.stylus support.type.property-name",
			"source.postcss support.type.property-name"
		  ],
		  "settings": {
			"foreground": "#92947A"
		  }
		},
		{
		  "scope": [
			"entity.name.module.js",
			"variable.import.parameter.js",
			"variable.other.class.js"
		  ],
		  "settings": {
			"foreground": "#A1B99D"
		  }
		},
		{
		  "scope": [
			"entity.name.method.js",
			"tag.decorator.js entity.name.tag.js",
			"tag.decorator.js punctuation.definition.tag.js"
		  ],
		  "settings": {
			"foreground": "#DBD0F6",
			"fontStyle": "italic"
		  }
		},
		{
		  "scope": [
			"entity.other.attribute-name",
			"support.function"
		  ],
		  "settings": {
			"foreground": "#DACD7D"
		  }
		},
		{
		  "scope": [
			"entity.other.attribute-name.id",
			"entity.other.attribute-name.class",
			"entity.other.attribute-name.pseudo-class",
			"entity.name.tag.css",
			"keyword.control.conditional.js",
			"support.constant",
			"entity.other.attribute-name.html",
			"string.quoted.single.js",
			"storage.type.function.js",
			"meta.object-literal.key"
		  ],
		  "settings": {
			"foreground": "#A3BE8C"
		  }
		},
		{
		  "scope": [
			"source.scss keyword.control"
		  ],
		  "settings": {
			"foreground": "#DACD7D"
		  }
		},
		{
		  "scope": [
			"markup.inserted"
		  ],
		  "settings": {
			"foreground": "#BCA427"
		  }
		},
		{
		  "scope": [
			"markup.deleted"
		  ],
		  "settings": {
			"foreground": "#A1B99D"
		  }
		},
		{
		  "scope": [
			"markup.changed"
		  ],
		  "settings": {
			"foreground": "#DACD7D"
		  }
		},
		{
		  "scope": [
			"string.regexp"
		  ],
		  "settings": {
			"foreground": "#DFDFEE"
		  }
		},
		{
		  "scope": [
			"constant.character.escape"
		  ],
		  "settings": {
			"foreground": "#DFDFEE"
		  }
		},
		{
		  "scope": [
			"*url*",
			"*link*",
			"*uri*"
		  ],
		  "settings": {
			"fontStyle": "underline"
		  }
		},
		{
		  "scope": [
			"source.js constant.other.object.key.js string.unquoted.label.js"
		  ],
		  "settings": {
			"foreground": "#A6C1D1",
			"fontStyle": "italic"
		  }
		},
		{
		  "scope": [
			"support.type.property-name.json"
		  ],
		  "settings": {
			"foreground": "#A6C1D1"
		  }
		},
		{
		  "scope": [
			"text.html.markdown",
			"punctuation.definition.list_item.markdown"
		  ],
		  "settings": {
			"foreground": "#A6C1D1"
		  }
		},
		{
		  "scope": [
			"text.html.markdown markup.inline.raw.markdown"
		  ],
		  "settings": {
			"foreground": "#DACD7D"
		  }
		},
		{
		  "scope": [
			"text.html.markdown markup.inline.raw.markdown",
			"punctuation.definition.raw.markdown"
		  ],
		  "settings": {
			"foreground": "#3F64BF50"
		  }
		},
		{
		  "scope": [
			"text.html.markdown meta.dummy.line-break"
		  ],
		  "settings": {}
		},
		{
		  "scope": [
			"markdown.heading",
			"markup.heading | markup.heading entity.name",
			"markup.heading.markdown punctuation.definition.heading.markdown",
			"entity.name.section.markdown"
		  ],
		  "settings": {
			"foreground": "#669EED",
			"fontStyle": "bold"
		  }
		},
		{
		  "scope": [
			"markup.underline"
		  ],
		  "settings": {
			"foreground": "#DBD0F6",
			"fontStyle": "underline"
		  }
		},
		{
		  "scope": [
			"markup.strike"
		  ],
		  "settings": {
			"fontStyle": ""
		  }
		},
		{
		  "scope": [
			"markup.quote punctuation.definition.blockquote.markdown"
		  ],
		  "settings": {
			"foreground": "#3F64BF50"
		  }
		},
		{
		  "scope": [
			"markup.quote"
		  ],
		  "settings": {
			"fontStyle": "italic"
		  }
		},
		{
		  "scope": [
			"string.other.link.description.title.markdown"
		  ],
		  "settings": {
			"foreground": "#DACD7D"
		  }
		},
		{
		  "scope": [
			"constant.other.reference.link.markdown"
		  ],
		  "settings": {
			"foreground": "#DACD7D"
		  }
		},
		{
		  "scope": [
			"markup.raw.block"
		  ],
		  "settings": {
			"foreground": "#DACD7D"
		  }
		},
		{
		  "scope": [
			"punctuation.definition.raw.markdown",
			"punctuation.definition.markdown"
		  ],
		  "settings": {
			"foreground": "#DFDFEE"
		  }
		},
		{
		  "scope": [
			"variable.language.fenced.markdown"
		  ],
		  "settings": {
			"foreground": "#3F64BF"
		  }
		},
		{
		  "scope": [
			"meta.separator"
		  ],
		  "settings": {
			"foreground": "#A7A8AF",
			"fontStyle": "bold"
		  }
		},
		{
		  "scope": "token.info-token",
		  "settings": {
			"foreground": "#3F64BF"
		  }
		},
		{
		  "scope": "token.warn-token",
		  "settings": {
			"foreground": "#DACD7D"
		  }
		},
		{
		  "scope": "token.error-token",
		  "settings": {
			"foreground": "#FF293B"
		  }
		},
		{
		  "scope": "token.debug-token",
		  "settings": {
			"foreground": "#DFDFEE"
		  }
		}
	  ]
  }